langchain_qianwen/__init__.py
langchain_qianwen/commons.py
langchain_qianwen/qwen_adaptor.py
langchain_qianwen/qwen_chat_model.py
langchain_qianwen/qwen_llm.py
langchain_qianwen/agents/__init__.py
langchain_qianwen/agents/mkrl_cn/__init__.py
langchain_qianwen/agents/mkrl_cn/prompt.py
langchain_qianwen/agents/mkrl_cn/zero_shot_agent_cn.py
langchain_qianwen/tools/__init__.py
langchain_qianwen/tools/code_interpreter.py
langchain_qianwen-0.1.17.dist-info/METADATA
langchain_qianwen-0.1.17.dist-info/WHEEL
langchain_qianwen-0.1.17.dist-info/top_level.txt
langchain_qianwen-0.1.17.dist-info/RECORD
