Metadata-Version: 2.1
Name: langchain-qianwen
Version: 0.1.17
Summary: 通义千问 Qianwen Langchain adapter
Home-page: https://github.com/DevinYF/langchain_qianwen
Author: Devin YF
Author-email: dyfsquall@qq.com
Classifier: Programming Language :: Python :: 3
Classifier: License :: OSI Approved :: MIT License
Classifier: Operating System :: OS Independent
Requires-Python: >=3.6
Requires-Dist: langchain (>=0.1.0)
Requires-Dist: dashscope (>=1.9.0)
